{
  "balance": 126.21,
  "initial_balance": 100.0,
  "strategies": [
    "Ensemble"
  ],
  "active_strategy": "all",
  "trades": [
    {
      "id": "7cc61ac7",
      "timestamp": "2026-02-08T20:30:04.825582+00:00",
      "strategy": "Ensemble",
      "direction": "DOWN",
      "confidence": 0.6833,
      "entry_price": 71025.7,
      "exit_price": 71088.91,
      "result": "LOSS",
      "profit": -0.5,
      "indicators": {
        "OpenVsCurrent": "DOWN",
        "BinanceOrderbook": "DOWN",
        "OrderbookImbalance": "DOWN"
      },
      "window_start": "2026-02-08T20:30:00+00:00",
      "window_end": "2026-02-08T20:45:00+00:00",
      "buy_price_cents": 50,
      "edge": 0.1783,
      "entry_minute": 0
    },
    {
      "id": "a25a94d2",
      "timestamp": "2026-02-08T20:31:12.266939+00:00",
      "strategy": "Ensemble",
      "direction": "DOWN",
      "confidence": 0.6573,
      "entry_price": 71025.7,
      "exit_price": 71088.91,
      "result": "LOSS",
      "profit": -0.5,
      "indicators": {
        "OpenVsCurrent": "DOWN",
        "BinanceOrderbook": "DOWN",
        "OrderbookImbalance": "DOWN"
      },
      "window_start": "2026-02-08T20:30:00+00:00",
      "window_end": "2026-02-08T20:45:00+00:00",
      "buy_price_cents": 50,
      "edge": 0.1623,
      "entry_minute": 1
    },
    {
      "id": "dfdb7ae1",
      "timestamp": "2026-02-08T20:33:02.981346+00:00",
      "strategy": "Ensemble",
      "direction": "UP",
      "confidence": 0.697,
      "entry_price": 71025.7,
      "exit_price": 71088.91,
      "result": "WIN",
      "profit": 0.5,
      "indicators": {
        "OpenVsCurrent": "UP",
        "BinanceOrderbook": "UP",
        "OrderbookImbalance": "DOWN"
      },
      "window_start": "2026-02-08T20:30:00+00:00",
      "window_end": "2026-02-08T20:45:00+00:00",
      "buy_price_cents": 50,
      "edge": 0.192,
      "entry_minute": 3
    },
    {
      "id": "850718bd",
      "timestamp": "2026-02-08T20:34:10.366586+00:00",
      "strategy": "Ensemble",
      "direction": "UP",
      "confidence": 0.7554,
      "entry_price": 71025.7,
      "exit_price": 71088.91,
      "result": "WIN",
      "profit": 0.5,
      "indicators": {
        "OpenVsCurrent": "UP",
        "BinanceOrderbook": "UP",
        "OrderbookImbalance": "DOWN"
      },
      "window_start": "2026-02-08T20:30:00+00:00",
      "window_end": "2026-02-08T20:45:00+00:00",
      "buy_price_cents": 50,
      "edge": 0.2504,
      "entry_minute": 4
    },
    {
      "id": "a7a0c892",
      "timestamp": "2026-02-08T20:35:04.711260+00:00",
      "strategy": "Ensemble",
      "direction": "UP",
      "confidence": 0.8957,
      "entry_price": 71025.7,
      "exit_price": 71088.91,
      "result": "WIN",
      "profit": 0.5,
      "indicators": {
        "OpenVsCurrent": "UP",
        "BinanceOrderbook": "UP"
      },
      "window_start": "2026-02-08T20:30:00+00:00",
      "window_end": "2026-02-08T20:45:00+00:00",
      "buy_price_cents": 50,
      "edge": 0.3907,
      "entry_minute": 5
    },
    {
      "id": "47eba03e",
      "timestamp": "2026-02-08T20:36:25.732345+00:00",
      "strategy": "Ensemble",
      "direction": "UP",
      "confidence": 0.6803,
      "entry_price": 71025.7,
      "exit_price": 71088.91,
      "result": "WIN",
      "profit": 0.5,
      "indicators": {
        "OpenVsCurrent": "UP",
        "BinanceOrderbook": "UP",
        "OrderbookImbalance": "DOWN"
      },
      "window_start": "2026-02-08T20:30:00+00:00",
      "window_end": "2026-02-08T20:45:00+00:00",
      "buy_price_cents": 50,
      "edge": 0.1753,
      "entry_minute": 6
    },
    {
      "id": "b4cc6354",
      "timestamp": "2026-02-08T20:37:06.132006+00:00",
      "strategy": "Ensemble",
      "direction": "UP",
      "confidence": 0.9277,
      "entry_price": 71025.7,
      "exit_price": 71088.91,
      "result": "WIN",
      "profit": 0.48,
      "indicators": {
        "OpenVsCurrent": "UP",
        "BinanceOrderbook": "UP"
      },
      "window_start": "2026-02-08T20:30:00+00:00",
      "window_end": "2026-02-08T20:45:00+00:00",
      "buy_price_cents": 52,
      "edge": 0.4127,
      "entry_minute": 7
    },
    {
      "id": "ebe53b91",
      "timestamp": "2026-02-08T20:38:00.313591+00:00",
      "strategy": "Ensemble",
      "direction": "UP",
      "confidence": 0.7671,
      "entry_price": 71025.7,
      "exit_price": 71088.91,
      "result": "WIN",
      "profit": 0.48,
      "indicators": {
        "OpenVsCurrent": "UP",
        "BinanceOrderbook": "UP",
        "OrderbookImbalance": "DOWN"
      },
      "window_start": "2026-02-08T20:30:00+00:00",
      "window_end": "2026-02-08T20:45:00+00:00",
      "buy_price_cents": 52,
      "edge": 0.2521,
      "entry_minute": 8
    },
    {
      "id": "82b46246",
      "timestamp": "2026-02-08T20:39:07.800064+00:00",
      "strategy": "Ensemble",
      "direction": "UP",
      "confidence": 0.6914,
      "entry_price": 71025.7,
      "exit_price": 71088.91,
      "result": "WIN",
      "profit": 0.48,
      "indicators": {
        "OpenVsCurrent": "UP",
        "BinanceOrderbook": "UP",
        "OrderbookImbalance": "DOWN"
      },
      "window_start": "2026-02-08T20:30:00+00:00",
      "window_end": "2026-02-08T20:45:00+00:00",
      "buy_price_cents": 52,
      "edge": 0.1764,
      "entry_minute": 9
    },
    {
      "id": "3d5977fd",
      "timestamp": "2026-02-08T20:42:17.578804+00:00",
      "strategy": "Ensemble",
      "direction": "UP",
      "confidence": 0.8895,
      "entry_price": 71025.7,
      "exit_price": 71088.91,
      "result": "WIN",
      "profit": 0.2,
      "indicators": {
        "OpenVsCurrent": "UP",
        "BinanceOrderbook": "UP",
        "OrderbookImbalance": "UP"
      },
      "window_start": "2026-02-08T20:30:00+00:00",
      "window_end": "2026-02-08T20:45:00+00:00",
      "buy_price_cents": 80,
      "edge": 0.0845,
      "entry_minute": 12
    },
    {
      "id": "76b9a1f3",
      "timestamp": "2026-02-08T20:45:54.804569+00:00",
      "strategy": "Ensemble",
      "direction": "DOWN",
      "confidence": 0.7435,
      "entry_price": 71088.92,
      "exit_price": 70835.17,
      "result": "WIN",
      "profit": 0.5,
      "indicators": {
        "OpenVsCurrent": "DOWN",
        "BinanceOrderbook": "DOWN",
        "OrderbookImbalance": "DOWN"
      },
      "window_start": "2026-02-08T20:45:00+00:00",
      "window_end": "2026-02-08T21:00:00+00:00",
      "buy_price_cents": 50,
      "edge": 0.2485,
      "entry_minute": 0
    },
    {
      "id": "35f594d9",
      "timestamp": "2026-02-08T20:47:04.060505+00:00",
      "strategy": "Ensemble",
      "direction": "DOWN",
      "confidence": 0.7248,
      "entry_price": 71088.92,
      "exit_price": 70835.17,
      "result": "WIN",
      "profit": 0.5,
      "indicators": {
        "OpenVsCurrent": "DOWN",
        "BinanceOrderbook": "DOWN",
        "OrderbookImbalance": "DOWN"
      },
      "window_start": "2026-02-08T20:45:00+00:00",
      "window_end": "2026-02-08T21:00:00+00:00",
      "buy_price_cents": 50,
      "edge": 0.2298,
      "entry_minute": 2
    },
    {
      "id": "04723828",
      "timestamp": "2026-02-08T20:49:36.007244+00:00",
      "strategy": "Ensemble",
      "direction": "DOWN",
      "confidence": 0.91,
      "entry_price": 71088.92,
      "exit_price": 70835.17,
      "result": "WIN",
      "profit": 0.5,
      "indicators": {
        "OpenVsCurrent": "DOWN",
        "BinanceOrderbook": "DOWN",
        "OrderbookImbalance": "DOWN"
      },
      "window_start": "2026-02-08T20:45:00+00:00",
      "window_end": "2026-02-08T21:00:00+00:00",
      "buy_price_cents": 50,
      "edge": 0.415,
      "entry_minute": 4
    },
    {
      "id": "5214a2a1",
      "timestamp": "2026-02-08T20:50:16.984651+00:00",
      "strategy": "Ensemble",
      "direction": "DOWN",
      "confidence": 0.915,
      "entry_price": 71088.92,
      "exit_price": 70835.17,
      "result": "WIN",
      "profit": 0.5,
      "indicators": {
        "OpenVsCurrent": "DOWN",
        "OrderbookImbalance": "DOWN"
      },
      "window_start": "2026-02-08T20:45:00+00:00",
      "window_end": "2026-02-08T21:00:00+00:00",
      "buy_price_cents": 50,
      "edge": 0.42,
      "entry_minute": 5
    },
    {
      "id": "41c80533",
      "timestamp": "2026-02-08T20:51:11.317357+00:00",
      "strategy": "Ensemble",
      "direction": "DOWN",
      "confidence": 0.8745,
      "entry_price": 71088.92,
      "exit_price": 70835.17,
      "result": "WIN",
      "profit": 0.5,
      "indicators": {
        "OpenVsCurrent": "DOWN",
        "BinanceOrderbook": "DOWN",
        "OrderbookImbalance": "DOWN"
      },
      "window_start": "2026-02-08T20:45:00+00:00",
      "window_end": "2026-02-08T21:00:00+00:00",
      "buy_price_cents": 50,
      "edge": 0.3795,
      "entry_minute": 6
    },
    {
      "id": "9111d189",
      "timestamp": "2026-02-08T20:52:05.768606+00:00",
      "strategy": "Ensemble",
      "direction": "DOWN",
      "confidence": 0.9031,
      "entry_price": 71088.92,
      "exit_price": 70835.17,
      "result": "WIN",
      "profit": 0.5,
      "indicators": {
        "OpenVsCurrent": "DOWN",
        "BinanceOrderbook": "DOWN",
        "OrderbookImbalance": "DOWN"
      },
      "window_start": "2026-02-08T20:45:00+00:00",
      "window_end": "2026-02-08T21:00:00+00:00",
      "buy_price_cents": 50,
      "edge": 0.4081,
      "entry_minute": 7
    },
    {
      "id": "f7a93f9d",
      "timestamp": "2026-02-08T20:53:00.284740+00:00",
      "strategy": "Ensemble",
      "direction": "DOWN",
      "confidence": 0.8443,
      "entry_price": 71088.92,
      "exit_price": 70835.17,
      "result": "WIN",
      "profit": 0.46,
      "indicators": {
        "OpenVsCurrent": "DOWN",
        "BinanceOrderbook": "DOWN",
        "OrderbookImbalance": "DOWN"
      },
      "window_start": "2026-02-08T20:45:00+00:00",
      "window_end": "2026-02-08T21:00:00+00:00",
      "buy_price_cents": 54,
      "edge": 0.3093,
      "entry_minute": 8
    },
    {
      "id": "5ce3ba20",
      "timestamp": "2026-02-08T20:54:08.038505+00:00",
      "strategy": "Ensemble",
      "direction": "DOWN",
      "confidence": 0.7518,
      "entry_price": 71088.92,
      "exit_price": 70835.17,
      "result": "WIN",
      "profit": 0.46,
      "indicators": {
        "OpenVsCurrent": "DOWN",
        "BinanceOrderbook": "DOWN",
        "OrderbookImbalance": "DOWN",
        "RSIDivergence": "UP"
      },
      "window_start": "2026-02-08T20:45:00+00:00",
      "window_end": "2026-02-08T21:00:00+00:00",
      "buy_price_cents": 54,
      "edge": 0.2168,
      "entry_minute": 9
    },
    {
      "id": "11407cb4",
      "timestamp": "2026-02-08T20:55:29.445490+00:00",
      "strategy": "Ensemble",
      "direction": "DOWN",
      "confidence": 0.9062,
      "entry_price": 71088.92,
      "exit_price": 70835.17,
      "result": "WIN",
      "profit": 0.46,
      "indicators": {
        "OpenVsCurrent": "DOWN",
        "BinanceOrderbook": "DOWN",
        "OrderbookImbalance": "DOWN"
      },
      "window_start": "2026-02-08T20:45:00+00:00",
      "window_end": "2026-02-08T21:00:00+00:00",
      "buy_price_cents": 54,
      "edge": 0.3712,
      "entry_minute": 10
    },
    {
      "id": "9802cfce",
      "timestamp": "2026-02-08T20:56:09.886538+00:00",
      "strategy": "Ensemble",
      "direction": "DOWN",
      "confidence": 0.8616,
      "entry_price": 71088.92,
      "exit_price": 70835.17,
      "result": "WIN",
      "profit": 0.46,
      "indicators": {
        "OpenVsCurrent": "DOWN",
        "BinanceOrderbook": "DOWN",
        "OrderbookImbalance": "DOWN"
      },
      "window_start": "2026-02-08T20:45:00+00:00",
      "window_end": "2026-02-08T21:00:00+00:00",
      "buy_price_cents": 54,
      "edge": 0.3266,
      "entry_minute": 11
    },
    {
      "id": "995281e0",
      "timestamp": "2026-02-08T20:57:31.222560+00:00",
      "strategy": "Ensemble",
      "direction": "DOWN",
      "confidence": 0.8559,
      "entry_price": 71088.92,
      "exit_price": 70835.17,
      "result": "WIN",
      "profit": 0.46,
      "indicators": {
        "OpenVsCurrent": "DOWN",
        "BinanceOrderbook": "DOWN",
        "OrderbookImbalance": "DOWN",
        "RSIDivergence": "DOWN"
      },
      "window_start": "2026-02-08T20:45:00+00:00",
      "window_end": "2026-02-08T21:00:00+00:00",
      "buy_price_cents": 54,
      "edge": 0.3209,
      "entry_minute": 12
    },
    {
      "id": "9beba0df",
      "timestamp": "2026-02-08T21:00:45.176847+00:00",
      "strategy": "Ensemble",
      "direction": "DOWN",
      "confidence": 0.7206,
      "entry_price": 70835.17,
      "exit_price": 71012.15,
      "result": "LOSS",
      "profit": -0.48,
      "indicators": {
        "OpenVsCurrent": "DOWN",
        "BinanceOrderbook": "DOWN",
        "OrderbookImbalance": "DOWN",
        "RSIDivergence": "UP"
      },
      "window_start": "2026-02-08T21:00:00+00:00",
      "window_end": "2026-02-08T21:15:00+00:00",
      "buy_price_cents": 48,
      "edge": 0.2356,
      "entry_minute": 0
    },
    {
      "id": "62721da7",
      "timestamp": "2026-02-08T21:01:12.259784+00:00",
      "strategy": "Ensemble",
      "direction": "DOWN",
      "confidence": 0.8774,
      "entry_price": 70835.17,
      "exit_price": 71012.15,
      "result": "LOSS",
      "profit": -0.48,
      "indicators": {
        "OpenVsCurrent": "DOWN",
        "BinanceOrderbook": "DOWN",
        "OrderbookImbalance": "DOWN"
      },
      "window_start": "2026-02-08T21:00:00+00:00",
      "window_end": "2026-02-08T21:15:00+00:00",
      "buy_price_cents": 48,
      "edge": 0.3924,
      "entry_minute": 1
    },
    {
      "id": "8ac4dbb3",
      "timestamp": "2026-02-08T21:03:01.045557+00:00",
      "strategy": "Ensemble",
      "direction": "UP",
      "confidence": 0.6516,
      "entry_price": 70835.17,
      "exit_price": 71012.15,
      "result": "WIN",
      "profit": 0.48,
      "indicators": {
        "OpenVsCurrent": "UP",
        "BinanceOrderbook": "UP",
        "OrderbookImbalance": "DOWN"
      },
      "window_start": "2026-02-08T21:00:00+00:00",
      "window_end": "2026-02-08T21:15:00+00:00",
      "buy_price_cents": 52,
      "edge": 0.1366,
      "entry_minute": 3
    },
    {
      "id": "074e4935",
      "timestamp": "2026-02-08T21:04:12.055425+00:00",
      "strategy": "Ensemble",
      "direction": "UP",
      "confidence": 0.724,
      "entry_price": 70835.17,
      "exit_price": 71012.15,
      "result": "WIN",
      "profit": 0.48,
      "indicators": {
        "OpenVsCurrent": "UP",
        "BinanceOrderbook": "UP",
        "OrderbookImbalance": "DOWN"
      },
      "window_start": "2026-02-08T21:00:00+00:00",
      "window_end": "2026-02-08T21:15:00+00:00",
      "buy_price_cents": 52,
      "edge": 0.209,
      "entry_minute": 4
    },
    {
      "id": "a5e678f1",
      "timestamp": "2026-02-08T21:06:00.310489+00:00",
      "strategy": "Ensemble",
      "direction": "UP",
      "confidence": 0.6411,
      "entry_price": 70835.17,
      "exit_price": 71012.15,
      "result": "WIN",
      "profit": 0.46,
      "indicators": {
        "OpenVsCurrent": "UP",
        "OrderbookImbalance": "DOWN"
      },
      "window_start": "2026-02-08T21:00:00+00:00",
      "window_end": "2026-02-08T21:15:00+00:00",
      "buy_price_cents": 54,
      "edge": 0.1061,
      "entry_minute": 6
    },
    {
      "id": "b6487dd7",
      "timestamp": "2026-02-08T21:07:21.420645+00:00",
      "strategy": "Ensemble",
      "direction": "UP",
      "confidence": 0.95,
      "entry_price": 70835.17,
      "exit_price": 71012.15,
      "result": "WIN",
      "profit": 0.46,
      "indicators": {
        "OpenVsCurrent": "UP"
      },
      "window_start": "2026-02-08T21:00:00+00:00",
      "window_end": "2026-02-08T21:15:00+00:00",
      "buy_price_cents": 54,
      "edge": 0.415,
      "entry_minute": 7
    },
    {
      "id": "5d99bf5f",
      "timestamp": "2026-02-08T21:08:15.739454+00:00",
      "strategy": "Ensemble",
      "direction": "UP",
      "confidence": 0.95,
      "entry_price": 70835.17,
      "exit_price": 71012.15,
      "result": "WIN",
      "profit": 0.46,
      "indicators": {
        "OpenVsCurrent": "UP"
      },
      "window_start": "2026-02-08T21:00:00+00:00",
      "window_end": "2026-02-08T21:15:00+00:00",
      "buy_price_cents": 54,
      "edge": 0.415,
      "entry_minute": 8
    },
    {
      "id": "ad9755db",
      "timestamp": "2026-02-08T21:09:09.774002+00:00",
      "strategy": "Ensemble",
      "direction": "UP",
      "confidence": 0.93,
      "entry_price": 70835.17,
      "exit_price": 71012.15,
      "result": "WIN",
      "profit": 0.46,
      "indicators": {
        "OpenVsCurrent": "UP",
        "BinanceOrderbook": "UP"
      },
      "window_start": "2026-02-08T21:00:00+00:00",
      "window_end": "2026-02-08T21:15:00+00:00",
      "buy_price_cents": 54,
      "edge": 0.395,
      "entry_minute": 9
    },
    {
      "id": "0b5d7239",
      "timestamp": "2026-02-08T21:10:04.525882+00:00",
      "strategy": "Ensemble",
      "direction": "UP",
      "confidence": 0.6996,
      "entry_price": 70835.17,
      "exit_price": 71012.15,
      "result": "WIN",
      "profit": 0.46,
      "indicators": {
        "OpenVsCurrent": "UP",
        "BinanceOrderbook": "UP",
        "RSIDivergence": "DOWN"
      },
      "window_start": "2026-02-08T21:00:00+00:00",
      "window_end": "2026-02-08T21:15:00+00:00",
      "buy_price_cents": 54,
      "edge": 0.1646,
      "entry_minute": 10
    },
    {
      "id": "47b1b4f8",
      "timestamp": "2026-02-08T21:11:01.350089+00:00",
      "strategy": "Ensemble",
      "direction": "UP",
      "confidence": 0.7933,
      "entry_price": 70835.17,
      "exit_price": 71012.15,
      "result": "WIN",
      "profit": 0.46,
      "indicators": {
        "OpenVsCurrent": "UP",
        "BinanceOrderbook": "UP",
        "RSIDivergence": "UP"
      },
      "window_start": "2026-02-08T21:00:00+00:00",
      "window_end": "2026-02-08T21:15:00+00:00",
      "buy_price_cents": 54,
      "edge": 0.2583,
      "entry_minute": 11
    },
    {
      "id": "bea0de2b",
      "timestamp": "2026-02-08T21:15:47.004675+00:00",
      "strategy": "Ensemble",
      "direction": "DOWN",
      "confidence": 0.6554,
      "entry_price": 71012.14,
      "exit_price": 70972.39,
      "result": "WIN",
      "profit": 0.5,
      "indicators": {
        "OpenVsCurrent": "DOWN",
        "BinanceOrderbook": "DOWN",
        "OrderbookImbalance": "DOWN"
      },
      "window_start": "2026-02-08T21:15:00+00:00",
      "window_end": "2026-02-08T21:30:00+00:00",
      "buy_price_cents": 50,
      "edge": 0.1604,
      "entry_minute": 0
    },
    {
      "id": "909957ba",
      "timestamp": "2026-02-08T21:16:00.651868+00:00",
      "strategy": "Ensemble",
      "direction": "DOWN",
      "confidence": 0.7053,
      "entry_price": 71012.14,
      "exit_price": 70972.39,
      "result": "WIN",
      "profit": 0.5,
      "indicators": {
        "OpenVsCurrent": "DOWN",
        "BinanceOrderbook": "DOWN",
        "OrderbookImbalance": "DOWN"
      },
      "window_start": "2026-02-08T21:15:00+00:00",
      "window_end": "2026-02-08T21:30:00+00:00",
      "buy_price_cents": 50,
      "edge": 0.2103,
      "entry_minute": 1
    },
    {
      "id": "a4b83abe",
      "timestamp": "2026-02-08T21:20:25.441810+00:00",
      "strategy": "Ensemble",
      "direction": "DOWN",
      "confidence": 0.744,
      "entry_price": 71012.14,
      "exit_price": 70972.39,
      "result": "WIN",
      "profit": 0.5,
      "indicators": {
        "OpenVsCurrent": "DOWN",
        "BinanceOrderbook": "DOWN",
        "OrderbookImbalance": "DOWN"
      },
      "window_start": "2026-02-08T21:15:00+00:00",
      "window_end": "2026-02-08T21:30:00+00:00",
      "buy_price_cents": 50,
      "edge": 0.249,
      "entry_minute": 5
    },
    {
      "id": "8eacb6f1",
      "timestamp": "2026-02-08T21:21:06.358623+00:00",
      "strategy": "Ensemble",
      "direction": "DOWN",
      "confidence": 0.8321,
      "entry_price": 71012.14,
      "exit_price": 70972.39,
      "result": "WIN",
      "profit": 0.5,
      "indicators": {
        "OpenVsCurrent": "DOWN",
        "BinanceOrderbook": "DOWN",
        "OrderbookImbalance": "DOWN"
      },
      "window_start": "2026-02-08T21:15:00+00:00",
      "window_end": "2026-02-08T21:30:00+00:00",
      "buy_price_cents": 50,
      "edge": 0.3371,
      "entry_minute": 6
    },
    {
      "id": "4f276b68",
      "timestamp": "2026-02-08T21:23:22.017187+00:00",
      "strategy": "Ensemble",
      "direction": "UP",
      "confidence": 0.7125,
      "entry_price": 71012.14,
      "exit_price": 70972.39,
      "result": "LOSS",
      "profit": -0.46,
      "indicators": {
        "OpenVsCurrent": "UP",
        "RSIDivergence": "DOWN"
      },
      "window_start": "2026-02-08T21:15:00+00:00",
      "window_end": "2026-02-08T21:30:00+00:00",
      "buy_price_cents": 46,
      "edge": 0.2575,
      "entry_minute": 8
    },
    {
      "id": "dfd39729",
      "timestamp": "2026-02-08T21:24:16.271140+00:00",
      "strategy": "Ensemble",
      "direction": "UP",
      "confidence": 0.7601,
      "entry_price": 71012.14,
      "exit_price": 70972.39,
      "result": "LOSS",
      "profit": -0.46,
      "indicators": {
        "OpenVsCurrent": "UP",
        "BinanceOrderbook": "UP",
        "OrderbookImbalance": "DOWN"
      },
      "window_start": "2026-02-08T21:15:00+00:00",
      "window_end": "2026-02-08T21:30:00+00:00",
      "buy_price_cents": 46,
      "edge": 0.3051,
      "entry_minute": 9
    },
    {
      "id": "bb69ee1a",
      "timestamp": "2026-02-08T21:25:37.899087+00:00",
      "strategy": "Ensemble",
      "direction": "UP",
      "confidence": 0.7198,
      "entry_price": 71012.14,
      "exit_price": 70972.39,
      "result": "LOSS",
      "profit": -0.46,
      "indicators": {
        "OpenVsCurrent": "UP",
        "BinanceOrderbook": "UP",
        "OrderbookImbalance": "DOWN"
      },
      "window_start": "2026-02-08T21:15:00+00:00",
      "window_end": "2026-02-08T21:30:00+00:00",
      "buy_price_cents": 46,
      "edge": 0.2648,
      "entry_minute": 10
    },
    {
      "id": "e48ab98c",
      "timestamp": "2026-02-08T21:26:04.827328+00:00",
      "strategy": "Ensemble",
      "direction": "DOWN",
      "confidence": 0.8447,
      "entry_price": 71012.14,
      "exit_price": 70972.39,
      "result": "WIN",
      "profit": 0.45,
      "indicators": {
        "BinanceOrderbook": "DOWN",
        "OrderbookImbalance": "DOWN"
      },
      "window_start": "2026-02-08T21:15:00+00:00",
      "window_end": "2026-02-08T21:30:00+00:00",
      "buy_price_cents": 55,
      "edge": 0.2997,
      "entry_minute": 11
    },
    {
      "id": "2ac8e353",
      "timestamp": "2026-02-08T21:28:19.772332+00:00",
      "strategy": "Ensemble",
      "direction": "DOWN",
      "confidence": 0.7241,
      "entry_price": 71012.14,
      "exit_price": 70972.39,
      "result": "WIN",
      "profit": 0.7,
      "indicators": {
        "OpenVsCurrent": "DOWN",
        "BinanceOrderbook": "DOWN",
        "OrderbookImbalance": "DOWN"
      },
      "window_start": "2026-02-08T21:15:00+00:00",
      "window_end": "2026-02-08T21:30:00+00:00",
      "buy_price_cents": 30,
      "edge": 0.4291,
      "entry_minute": 13
    },
    {
      "id": "349eb0f4",
      "timestamp": "2026-02-08T21:29:00.544240+00:00",
      "strategy": "Ensemble",
      "direction": "DOWN",
      "confidence": 0.7013,
      "entry_price": 71012.14,
      "exit_price": 70972.39,
      "result": "WIN",
      "profit": 0.7,
      "indicators": {
        "OpenVsCurrent": "DOWN",
        "BinanceOrderbook": "DOWN",
        "OrderbookImbalance": "DOWN"
      },
      "window_start": "2026-02-08T21:15:00+00:00",
      "window_end": "2026-02-08T21:30:00+00:00",
      "buy_price_cents": 30,
      "edge": 0.4063,
      "entry_minute": 14
    },
    {
      "id": "28a7060f",
      "timestamp": "2026-02-08T21:30:34.788841+00:00",
      "strategy": "Ensemble",
      "direction": "UP",
      "confidence": 0.6312,
      "entry_price": 70972.39,
      "exit_price": 70766.79,
      "result": "LOSS",
      "profit": -0.5,
      "indicators": {
        "OpenVsCurrent": "UP",
        "BinanceOrderbook": "UP",
        "OrderbookImbalance": "DOWN"
      },
      "window_start": "2026-02-08T21:30:00+00:00",
      "window_end": "2026-02-08T21:45:00+00:00",
      "buy_price_cents": 50,
      "edge": 0.1362,
      "entry_minute": 0
    },
    {
      "id": "d0cc7b3f",
      "timestamp": "2026-02-08T21:31:15.425014+00:00",
      "strategy": "Ensemble",
      "direction": "DOWN",
      "confidence": 0.6826,
      "entry_price": 70972.39,
      "exit_price": 70766.79,
      "result": "WIN",
      "profit": 0.5,
      "indicators": {
        "OpenVsCurrent": "DOWN",
        "BinanceOrderbook": "DOWN",
        "OrderbookImbalance": "DOWN"
      },
      "window_start": "2026-02-08T21:30:00+00:00",
      "window_end": "2026-02-08T21:45:00+00:00",
      "buy_price_cents": 50,
      "edge": 0.1776,
      "entry_minute": 1
    },
    {
      "id": "4b5d7ec8",
      "timestamp": "2026-02-08T21:32:09.618736+00:00",
      "strategy": "Ensemble",
      "direction": "DOWN",
      "confidence": 0.8799,
      "entry_price": 70972.39,
      "exit_price": 70766.79,
      "result": "WIN",
      "profit": 0.5,
      "indicators": {
        "OpenVsCurrent": "DOWN",
        "BinanceOrderbook": "DOWN",
        "OrderbookImbalance": "DOWN"
      },
      "window_start": "2026-02-08T21:30:00+00:00",
      "window_end": "2026-02-08T21:45:00+00:00",
      "buy_price_cents": 50,
      "edge": 0.3749,
      "entry_minute": 2
    },
    {
      "id": "09b79dbb",
      "timestamp": "2026-02-08T21:33:04.091002+00:00",
      "strategy": "Ensemble",
      "direction": "DOWN",
      "confidence": 0.831,
      "entry_price": 70972.39,
      "exit_price": 70766.79,
      "result": "WIN",
      "profit": 0.5,
      "indicators": {
        "OpenVsCurrent": "DOWN",
        "BinanceOrderbook": "DOWN",
        "OrderbookImbalance": "DOWN"
      },
      "window_start": "2026-02-08T21:30:00+00:00",
      "window_end": "2026-02-08T21:45:00+00:00",
      "buy_price_cents": 50,
      "edge": 0.326,
      "entry_minute": 3
    },
    {
      "id": "dd40c6d4",
      "timestamp": "2026-02-08T21:34:25.879954+00:00",
      "strategy": "Ensemble",
      "direction": "DOWN",
      "confidence": 0.9079,
      "entry_price": 70972.39,
      "exit_price": 70766.79,
      "result": "WIN",
      "profit": 0.5,
      "indicators": {
        "OpenVsCurrent": "DOWN",
        "OrderbookImbalance": "DOWN"
      },
      "window_start": "2026-02-08T21:30:00+00:00",
      "window_end": "2026-02-08T21:45:00+00:00",
      "buy_price_cents": 50,
      "edge": 0.4029,
      "entry_minute": 4
    },
    {
      "id": "9f7c944d",
      "timestamp": "2026-02-08T21:35:47.880790+00:00",
      "strategy": "Ensemble",
      "direction": "DOWN",
      "confidence": 0.9142,
      "entry_price": 70972.39,
      "exit_price": 70766.79,
      "result": "WIN",
      "profit": 0.6,
      "indicators": {
        "OpenVsCurrent": "DOWN",
        "OrderbookImbalance": "DOWN"
      },
      "window_start": "2026-02-08T21:30:00+00:00",
      "window_end": "2026-02-08T21:45:00+00:00",
      "buy_price_cents": 40,
      "edge": 0.5192,
      "entry_minute": 5
    },
    {
      "id": "39036479",
      "timestamp": "2026-02-08T21:36:01.355772+00:00",
      "strategy": "Ensemble",
      "direction": "DOWN",
      "confidence": 0.8563,
      "entry_price": 70972.39,
      "exit_price": 70766.79,
      "result": "WIN",
      "profit": 0.6,
      "indicators": {
        "OpenVsCurrent": "DOWN",
        "BinanceOrderbook": "DOWN",
        "OrderbookImbalance": "DOWN"
      },
      "window_start": "2026-02-08T21:30:00+00:00",
      "window_end": "2026-02-08T21:45:00+00:00",
      "buy_price_cents": 40,
      "edge": 0.4613,
      "entry_minute": 6
    },
    {
      "id": "e84a1ca1",
      "timestamp": "2026-02-08T21:37:24.624575+00:00",
      "strategy": "Ensemble",
      "direction": "DOWN",
      "confidence": 0.9105,
      "entry_price": 70972.39,
      "exit_price": 70766.79,
      "result": "WIN",
      "profit": 0.6,
      "indicators": {
        "OpenVsCurrent": "DOWN",
        "BinanceOrderbook": "DOWN",
        "OrderbookImbalance": "DOWN"
      },
      "window_start": "2026-02-08T21:30:00+00:00",
      "window_end": "2026-02-08T21:45:00+00:00",
      "buy_price_cents": 40,
      "edge": 0.5155,
      "entry_minute": 7
    },
    {
      "id": "f6772a59",
      "timestamp": "2026-02-08T21:38:05.942610+00:00",
      "strategy": "Ensemble",
      "direction": "DOWN",
      "confidence": 0.9162,
      "entry_price": 70972.39,
      "exit_price": 70766.79,
      "result": "WIN",
      "profit": 0.6,
      "indicators": {
        "OpenVsCurrent": "DOWN",
        "OrderbookImbalance": "DOWN"
      },
      "window_start": "2026-02-08T21:30:00+00:00",
      "window_end": "2026-02-08T21:45:00+00:00",
      "buy_price_cents": 40,
      "edge": 0.5212,
      "entry_minute": 8
    },
    {
      "id": "a559df08",
      "timestamp": "2026-02-08T21:39:54.466082+00:00",
      "strategy": "Ensemble",
      "direction": "DOWN",
      "confidence": 0.8957,
      "entry_price": 70972.39,
      "exit_price": 70766.79,
      "result": "WIN",
      "profit": 0.2,
      "indicators": {
        "OpenVsCurrent": "DOWN",
        "BinanceOrderbook": "DOWN",
        "OrderbookImbalance": "DOWN"
      },
      "window_start": "2026-02-08T21:30:00+00:00",
      "window_end": "2026-02-08T21:45:00+00:00",
      "buy_price_cents": 80,
      "edge": 0.1007,
      "entry_minute": 9
    },
    {
      "id": "6771b5a7",
      "timestamp": "2026-02-08T21:47:08.979455+00:00",
      "strategy": "Ensemble",
      "direction": "UP",
      "confidence": 0.6727,
      "entry_price": 70766.79,
      "exit_price": 70700.0,
      "result": "LOSS",
      "profit": -0.52,
      "indicators": {
        "OpenVsCurrent": "UP",
        "BinanceOrderbook": "UP",
        "OrderbookImbalance": "DOWN"
      },
      "window_start": "2026-02-08T21:45:00+00:00",
      "window_end": "2026-02-08T22:00:00+00:00",
      "buy_price_cents": 52,
      "edge": 0.1577,
      "entry_minute": 2
    },
    {
      "id": "ce2a0978",
      "timestamp": "2026-02-08T21:48:29.953751+00:00",
      "strategy": "Ensemble",
      "direction": "UP",
      "confidence": 0.7125,
      "entry_price": 70766.79,
      "exit_price": 70700.0,
      "result": "LOSS",
      "profit": -0.55,
      "indicators": {
        "OpenVsCurrent": "UP",
        "OrderbookImbalance": "DOWN"
      },
      "window_start": "2026-02-08T21:45:00+00:00",
      "window_end": "2026-02-08T22:00:00+00:00",
      "buy_price_cents": 55,
      "edge": 0.1675,
      "entry_minute": 3
    },
    {
      "id": "c2f05886",
      "timestamp": "2026-02-08T21:50:05.161869+00:00",
      "strategy": "Ensemble",
      "direction": "DOWN",
      "confidence": 0.7199,
      "entry_price": 70766.79,
      "exit_price": 70700.0,
      "result": "WIN",
      "profit": 0.54,
      "indicators": {
        "OpenVsCurrent": "DOWN",
        "BinanceOrderbook": "DOWN",
        "OrderbookImbalance": "DOWN",
        "RSIDivergence": "UP"
      },
      "window_start": "2026-02-08T21:45:00+00:00",
      "window_end": "2026-02-08T22:00:00+00:00",
      "buy_price_cents": 46,
      "edge": 0.2649,
      "entry_minute": 5
    },
    {
      "id": "a8a1a7be",
      "timestamp": "2026-02-08T21:51:26.751051+00:00",
      "strategy": "Ensemble",
      "direction": "DOWN",
      "confidence": 0.7275,
      "entry_price": 70766.79,
      "exit_price": 70700.0,
      "result": "WIN",
      "profit": 0.56,
      "indicators": {
        "OpenVsCurrent": "DOWN",
        "OrderbookImbalance": "DOWN",
        "RSIDivergence": "UP"
      },
      "window_start": "2026-02-08T21:45:00+00:00",
      "window_end": "2026-02-08T22:00:00+00:00",
      "buy_price_cents": 44,
      "edge": 0.2825,
      "entry_minute": 6
    },
    {
      "id": "d924cdba",
      "timestamp": "2026-02-08T21:52:07.685250+00:00",
      "strategy": "Ensemble",
      "direction": "DOWN",
      "confidence": 0.8266,
      "entry_price": 70766.79,
      "exit_price": 70700.0,
      "result": "WIN",
      "profit": 0.56,
      "indicators": {
        "OpenVsCurrent": "DOWN",
        "BinanceOrderbook": "DOWN",
        "OrderbookImbalance": "DOWN"
      },
      "window_start": "2026-02-08T21:45:00+00:00",
      "window_end": "2026-02-08T22:00:00+00:00",
      "buy_price_cents": 44,
      "edge": 0.3816,
      "entry_minute": 7
    },
    {
      "id": "d744c7be",
      "timestamp": "2026-02-08T21:53:02.073151+00:00",
      "strategy": "Ensemble",
      "direction": "DOWN",
      "confidence": 0.821,
      "entry_price": 70766.79,
      "exit_price": 70700.0,
      "result": "WIN",
      "profit": 0.56,
      "indicators": {
        "OpenVsCurrent": "DOWN",
        "BinanceOrderbook": "DOWN",
        "OrderbookImbalance": "DOWN"
      },
      "window_start": "2026-02-08T21:45:00+00:00",
      "window_end": "2026-02-08T22:00:00+00:00",
      "buy_price_cents": 44,
      "edge": 0.376,
      "entry_minute": 8
    },
    {
      "id": "e2a241e3",
      "timestamp": "2026-02-08T21:54:09.959361+00:00",
      "strategy": "Ensemble",
      "direction": "DOWN",
      "confidence": 0.8507,
      "entry_price": 70766.79,
      "exit_price": 70700.0,
      "result": "WIN",
      "profit": 0.56,
      "indicators": {
        "OpenVsCurrent": "DOWN",
        "BinanceOrderbook": "DOWN",
        "OrderbookImbalance": "DOWN"
      },
      "window_start": "2026-02-08T21:45:00+00:00",
      "window_end": "2026-02-08T22:00:00+00:00",
      "buy_price_cents": 44,
      "edge": 0.4057,
      "entry_minute": 9
    },
    {
      "id": "4eebbfdc",
      "timestamp": "2026-02-08T21:55:04.301939+00:00",
      "strategy": "Ensemble",
      "direction": "DOWN",
      "confidence": 0.8049,
      "entry_price": 70766.79,
      "exit_price": 70700.0,
      "result": "WIN",
      "profit": 0.56,
      "indicators": {
        "OpenVsCurrent": "DOWN",
        "BinanceOrderbook": "DOWN",
        "OrderbookImbalance": "DOWN",
        "RSIDivergence": "DOWN"
      },
      "window_start": "2026-02-08T21:45:00+00:00",
      "window_end": "2026-02-08T22:00:00+00:00",
      "buy_price_cents": 44,
      "edge": 0.3599,
      "entry_minute": 10
    },
    {
      "id": "10aacfb3",
      "timestamp": "2026-02-08T21:56:25.843363+00:00",
      "strategy": "Ensemble",
      "direction": "DOWN",
      "confidence": 0.8249,
      "entry_price": 70766.79,
      "exit_price": 70700.0,
      "result": "WIN",
      "profit": 0.56,
      "indicators": {
        "OpenVsCurrent": "DOWN",
        "BinanceOrderbook": "DOWN",
        "OrderbookImbalance": "DOWN"
      },
      "window_start": "2026-02-08T21:45:00+00:00",
      "window_end": "2026-02-08T22:00:00+00:00",
      "buy_price_cents": 44,
      "edge": 0.3799,
      "entry_minute": 11
    },
    {
      "id": "3cf29b70",
      "timestamp": "2026-02-08T21:57:34.361247+00:00",
      "strategy": "Ensemble",
      "direction": "DOWN",
      "confidence": 0.9164,
      "entry_price": 70766.79,
      "exit_price": 70700.0,
      "result": "WIN",
      "profit": 0.33,
      "indicators": {
        "OpenVsCurrent": "DOWN",
        "OrderbookImbalance": "DOWN"
      },
      "window_start": "2026-02-08T21:45:00+00:00",
      "window_end": "2026-02-08T22:00:00+00:00",
      "buy_price_cents": 67,
      "edge": 0.2464,
      "entry_minute": 12
    },
    {
      "id": "217cfb99",
      "timestamp": "2026-02-08T21:58:15.309423+00:00",
      "strategy": "Ensemble",
      "direction": "DOWN",
      "confidence": 0.9162,
      "entry_price": 70766.79,
      "exit_price": 70700.0,
      "result": "WIN",
      "profit": 0.33,
      "indicators": {
        "OpenVsCurrent": "DOWN",
        "OrderbookImbalance": "DOWN"
      },
      "window_start": "2026-02-08T21:45:00+00:00",
      "window_end": "2026-02-08T22:00:00+00:00",
      "buy_price_cents": 67,
      "edge": 0.2462,
      "entry_minute": 13
    },
    {
      "id": "c56df7ec",
      "timestamp": "2026-02-08T21:59:23.878710+00:00",
      "strategy": "Ensemble",
      "direction": "DOWN",
      "confidence": 0.7668,
      "entry_price": 70766.79,
      "exit_price": 70700.0,
      "result": "WIN",
      "profit": 0.33,
      "indicators": {
        "OpenVsCurrent": "DOWN",
        "BinanceOrderbook": "DOWN",
        "OrderbookImbalance": "DOWN",
        "RSIDivergence": "DOWN"
      },
      "window_start": "2026-02-08T21:45:00+00:00",
      "window_end": "2026-02-08T22:00:00+00:00",
      "buy_price_cents": 67,
      "edge": 0.0968,
      "entry_minute": 14
    },
    {
      "id": "91769613",
      "timestamp": "2026-02-08T22:01:15.225996+00:00",
      "strategy": "Ensemble",
      "direction": "DOWN",
      "confidence": 0.6965,
      "entry_price": 70700.01,
      "exit_price": 70835.63,
      "result": "LOSS",
      "profit": -0.46,
      "indicators": {
        "BinanceOrderbook": "DOWN",
        "OrderbookImbalance": "DOWN"
      },
      "window_start": "2026-02-08T22:00:00+00:00",
      "window_end": "2026-02-08T22:15:00+00:00",
      "buy_price_cents": 46,
      "edge": 0.2415,
      "entry_minute": 1
    },
    {
      "id": "0991f3ab",
      "timestamp": "2026-02-08T22:02:09.635230+00:00",
      "strategy": "Ensemble",
      "direction": "DOWN",
      "confidence": 0.712,
      "entry_price": 70700.01,
      "exit_price": 70835.63,
      "result": "LOSS",
      "profit": -0.46,
      "indicators": {
        "OrderbookImbalance": "DOWN"
      },
      "window_start": "2026-02-08T22:00:00+00:00",
      "window_end": "2026-02-08T22:15:00+00:00",
      "buy_price_cents": 46,
      "edge": 0.257,
      "entry_minute": 2
    },
    {
      "id": "be7fc63c",
      "timestamp": "2026-02-08T22:03:05.112533+00:00",
      "strategy": "Ensemble",
      "direction": "UP",
      "confidence": 0.6874,
      "entry_price": 70700.01,
      "exit_price": 70835.63,
      "result": "WIN",
      "profit": 0.45,
      "indicators": {
        "OpenVsCurrent": "UP",
        "OrderbookImbalance": "DOWN"
      },
      "window_start": "2026-02-08T22:00:00+00:00",
      "window_end": "2026-02-08T22:15:00+00:00",
      "buy_price_cents": 55,
      "edge": 0.1424,
      "entry_minute": 3
    },
    {
      "id": "416342ee",
      "timestamp": "2026-02-08T22:04:27.612087+00:00",
      "strategy": "Ensemble",
      "direction": "UP",
      "confidence": 0.6464,
      "entry_price": 70700.01,
      "exit_price": 70835.63,
      "result": "WIN",
      "profit": 0.45,
      "indicators": {
        "OpenVsCurrent": "UP",
        "BinanceOrderbook": "UP",
        "OrderbookImbalance": "DOWN"
      },
      "window_start": "2026-02-08T22:00:00+00:00",
      "window_end": "2026-02-08T22:15:00+00:00",
      "buy_price_cents": 55,
      "edge": 0.1014,
      "entry_minute": 4
    },
    {
      "id": "212c9472",
      "timestamp": "2026-02-08T22:05:08.775593+00:00",
      "strategy": "Ensemble",
      "direction": "UP",
      "confidence": 0.6888,
      "entry_price": 70700.01,
      "exit_price": 70835.63,
      "result": "WIN",
      "profit": 0.45,
      "indicators": {
        "OpenVsCurrent": "UP",
        "BinanceOrderbook": "UP",
        "OrderbookImbalance": "DOWN"
      },
      "window_start": "2026-02-08T22:00:00+00:00",
      "window_end": "2026-02-08T22:15:00+00:00",
      "buy_price_cents": 55,
      "edge": 0.1438,
      "entry_minute": 5
    },
    {
      "id": "58287c86",
      "timestamp": "2026-02-08T22:06:16.621041+00:00",
      "strategy": "Ensemble",
      "direction": "UP",
      "confidence": 0.6435,
      "entry_price": 70700.01,
      "exit_price": 70835.63,
      "result": "WIN",
      "profit": 0.45,
      "indicators": {
        "OpenVsCurrent": "UP",
        "BinanceOrderbook": "UP",
        "OrderbookImbalance": "DOWN",
        "RSIDivergence": "DOWN"
      },
      "window_start": "2026-02-08T22:00:00+00:00",
      "window_end": "2026-02-08T22:15:00+00:00",
      "buy_price_cents": 55,
      "edge": 0.0985,
      "entry_minute": 6
    },
    {
      "id": "640a69c3",
      "timestamp": "2026-02-08T22:07:24.260993+00:00",
      "strategy": "Ensemble",
      "direction": "UP",
      "confidence": 0.7125,
      "entry_price": 70700.01,
      "exit_price": 70835.63,
      "result": "WIN",
      "profit": 0.45,
      "indicators": {
        "OpenVsCurrent": "UP",
        "RSIDivergence": "DOWN"
      },
      "window_start": "2026-02-08T22:00:00+00:00",
      "window_end": "2026-02-08T22:15:00+00:00",
      "buy_price_cents": 55,
      "edge": 0.1675,
      "entry_minute": 7
    },
    {
      "id": "1844be2e",
      "timestamp": "2026-02-08T22:08:05.287215+00:00",
      "strategy": "Ensemble",
      "direction": "UP",
      "confidence": 0.7043,
      "entry_price": 70700.01,
      "exit_price": 70835.63,
      "result": "WIN",
      "profit": 0.45,
      "indicators": {
        "OpenVsCurrent": "UP",
        "BinanceOrderbook": "UP",
        "RSIDivergence": "DOWN"
      },
      "window_start": "2026-02-08T22:00:00+00:00",
      "window_end": "2026-02-08T22:15:00+00:00",
      "buy_price_cents": 55,
      "edge": 0.1543,
      "entry_minute": 8
    },
    {
      "id": "012c1830",
      "timestamp": "2026-02-08T22:09:13.326907+00:00",
      "strategy": "Ensemble",
      "direction": "UP",
      "confidence": 0.7004,
      "entry_price": 70700.01,
      "exit_price": 70835.63,
      "result": "WIN",
      "profit": 0.45,
      "indicators": {
        "OpenVsCurrent": "UP",
        "BinanceOrderbook": "UP",
        "OrderbookImbalance": "DOWN"
      },
      "window_start": "2026-02-08T22:00:00+00:00",
      "window_end": "2026-02-08T22:15:00+00:00",
      "buy_price_cents": 55,
      "edge": 0.1504,
      "entry_minute": 9
    },
    {
      "id": "fdb1ac1a",
      "timestamp": "2026-02-08T22:10:21.080359+00:00",
      "strategy": "Ensemble",
      "direction": "UP",
      "confidence": 0.6433,
      "entry_price": 70700.01,
      "exit_price": 70835.63,
      "result": "WIN",
      "profit": 0.45,
      "indicators": {
        "OpenVsCurrent": "UP",
        "BinanceOrderbook": "UP",
        "OrderbookImbalance": "DOWN"
      },
      "window_start": "2026-02-08T22:00:00+00:00",
      "window_end": "2026-02-08T22:15:00+00:00",
      "buy_price_cents": 55,
      "edge": 0.0933,
      "entry_minute": 10
    },
    {
      "id": "e42874c7",
      "timestamp": "2026-02-08T22:11:55.993831+00:00",
      "strategy": "Ensemble",
      "direction": "UP",
      "confidence": 0.6493,
      "entry_price": 70700.01,
      "exit_price": 70835.63,
      "result": "WIN",
      "profit": 0.46,
      "indicators": {
        "OpenVsCurrent": "UP",
        "BinanceOrderbook": "UP",
        "OrderbookImbalance": "DOWN"
      },
      "window_start": "2026-02-08T22:00:00+00:00",
      "window_end": "2026-02-08T22:15:00+00:00",
      "buy_price_cents": 54,
      "edge": 0.1143,
      "entry_minute": 11
    },
    {
      "id": "91e6969f",
      "timestamp": "2026-02-08T22:12:09.793854+00:00",
      "strategy": "Ensemble",
      "direction": "UP",
      "confidence": 0.6924,
      "entry_price": 70700.01,
      "exit_price": 70835.63,
      "result": "WIN",
      "profit": 0.46,
      "indicators": {
        "OpenVsCurrent": "UP",
        "BinanceOrderbook": "UP",
        "OrderbookImbalance": "DOWN"
      },
      "window_start": "2026-02-08T22:00:00+00:00",
      "window_end": "2026-02-08T22:15:00+00:00",
      "buy_price_cents": 54,
      "edge": 0.1574,
      "entry_minute": 12
    },
    {
      "id": "db3c88ce",
      "timestamp": "2026-02-08T22:13:04.097310+00:00",
      "strategy": "Ensemble",
      "direction": "UP",
      "confidence": 0.9085,
      "entry_price": 70700.01,
      "exit_price": 70835.63,
      "result": "WIN",
      "profit": 0.46,
      "indicators": {
        "OpenVsCurrent": "UP",
        "BinanceOrderbook": "UP"
      },
      "window_start": "2026-02-08T22:00:00+00:00",
      "window_end": "2026-02-08T22:15:00+00:00",
      "buy_price_cents": 54,
      "edge": 0.3735,
      "entry_minute": 13
    },
    {
      "id": "dd70bbb6",
      "timestamp": "2026-02-08T22:14:11.755089+00:00",
      "strategy": "Ensemble",
      "direction": "UP",
      "confidence": 0.6643,
      "entry_price": 70700.01,
      "exit_price": 70835.63,
      "result": "WIN",
      "profit": 0.46,
      "indicators": {
        "OpenVsCurrent": "UP",
        "BinanceOrderbook": "UP",
        "OrderbookImbalance": "DOWN",
        "RSIDivergence": "DOWN"
      },
      "window_start": "2026-02-08T22:00:00+00:00",
      "window_end": "2026-02-08T22:15:00+00:00",
      "buy_price_cents": 54,
      "edge": 0.1293,
      "entry_minute": 14
    },
    {
      "id": "395af4af",
      "timestamp": "2026-02-08T22:15:05.972091+00:00",
      "strategy": "Ensemble",
      "direction": "DOWN",
      "confidence": 0.6812,
      "entry_price": 70835.63,
      "exit_price": 70851.43,
      "result": "LOSS",
      "profit": -0.5,
      "indicators": {
        "OpenVsCurrent": "DOWN",
        "BinanceOrderbook": "DOWN",
        "OrderbookImbalance": "DOWN"
      },
      "window_start": "2026-02-08T22:15:00+00:00",
      "window_end": "2026-02-08T22:30:00+00:00",
      "buy_price_cents": 50,
      "edge": 0.1862,
      "entry_minute": 0
    },
    {
      "id": "65642214",
      "timestamp": "2026-02-08T22:16:34.788170+00:00",
      "strategy": "Ensemble",
      "direction": "DOWN",
      "confidence": 0.6958,
      "entry_price": 70835.63,
      "exit_price": 70851.43,
      "result": "LOSS",
      "profit": -0.5,
      "indicators": {
        "BinanceOrderbook": "DOWN",
        "OrderbookImbalance": "DOWN"
      },
      "window_start": "2026-02-08T22:15:00+00:00",
      "window_end": "2026-02-08T22:30:00+00:00",
      "buy_price_cents": 50,
      "edge": 0.2008,
      "entry_minute": 1
    },
    {
      "id": "5d03bf13",
      "timestamp": "2026-02-08T22:17:02.470071+00:00",
      "strategy": "Ensemble",
      "direction": "DOWN",
      "confidence": 0.6307,
      "entry_price": 70835.63,
      "exit_price": 70851.43,
      "result": "LOSS",
      "profit": -0.5,
      "indicators": {
        "OrderbookImbalance": "DOWN",
        "RSIDivergence": "DOWN"
      },
      "window_start": "2026-02-08T22:15:00+00:00",
      "window_end": "2026-02-08T22:30:00+00:00",
      "buy_price_cents": 50,
      "edge": 0.1357,
      "entry_minute": 2
    },
    {
      "id": "e8a2590e",
      "timestamp": "2026-02-08T22:19:45.399141+00:00",
      "strategy": "Ensemble",
      "direction": "UP",
      "confidence": 0.7419,
      "entry_price": 70835.63,
      "exit_price": 70851.43,
      "result": "WIN",
      "profit": 0.5,
      "indicators": {
        "OpenVsCurrent": "UP",
        "BinanceOrderbook": "UP",
        "OrderbookImbalance": "DOWN"
      },
      "window_start": "2026-02-08T22:15:00+00:00",
      "window_end": "2026-02-08T22:30:00+00:00",
      "buy_price_cents": 50,
      "edge": 0.2369,
      "entry_minute": 4
    },
    {
      "id": "e0ff91c0",
      "timestamp": "2026-02-08T22:20:12.633038+00:00",
      "strategy": "Ensemble",
      "direction": "UP",
      "confidence": 0.7423,
      "entry_price": 70835.63,
      "exit_price": 70851.43,
      "result": "WIN",
      "profit": 0.5,
      "indicators": {
        "OpenVsCurrent": "UP",
        "BinanceOrderbook": "UP",
        "OrderbookImbalance": "DOWN"
      },
      "window_start": "2026-02-08T22:15:00+00:00",
      "window_end": "2026-02-08T22:30:00+00:00",
      "buy_price_cents": 50,
      "edge": 0.2373,
      "entry_minute": 5
    },
    {
      "id": "187654cb",
      "timestamp": "2026-02-08T22:21:34.269833+00:00",
      "strategy": "Ensemble",
      "direction": "UP",
      "confidence": 0.7125,
      "entry_price": 70835.63,
      "exit_price": 70851.43,
      "result": "WIN",
      "profit": 0.5,
      "indicators": {
        "OpenVsCurrent": "UP",
        "OrderbookImbalance": "DOWN"
      },
      "window_start": "2026-02-08T22:15:00+00:00",
      "window_end": "2026-02-08T22:30:00+00:00",
      "buy_price_cents": 50,
      "edge": 0.2075,
      "entry_minute": 6
    },
    {
      "id": "1c411be9",
      "timestamp": "2026-02-08T22:22:15.174827+00:00",
      "strategy": "Ensemble",
      "direction": "UP",
      "confidence": 0.6462,
      "entry_price": 70835.63,
      "exit_price": 70851.43,
      "result": "WIN",
      "profit": 0.46,
      "indicators": {
        "OpenVsCurrent": "UP",
        "BinanceOrderbook": "UP",
        "OrderbookImbalance": "DOWN",
        "RSIDivergence": "UP"
      },
      "window_start": "2026-02-08T22:15:00+00:00",
      "window_end": "2026-02-08T22:30:00+00:00",
      "buy_price_cents": 54,
      "edge": 0.1112,
      "entry_minute": 7
    },
    {
      "id": "de3bd481",
      "timestamp": "2026-02-08T22:23:23.420195+00:00",
      "strategy": "Ensemble",
      "direction": "UP",
      "confidence": 0.6676,
      "entry_price": 70835.63,
      "exit_price": 70851.43,
      "result": "WIN",
      "profit": 0.46,
      "indicators": {
        "OpenVsCurrent": "UP",
        "OrderbookImbalance": "DOWN"
      },
      "window_start": "2026-02-08T22:15:00+00:00",
      "window_end": "2026-02-08T22:30:00+00:00",
      "buy_price_cents": 54,
      "edge": 0.1326,
      "entry_minute": 8
    },
    {
      "id": "865f05e7",
      "timestamp": "2026-02-08T22:24:04.477545+00:00",
      "strategy": "Ensemble",
      "direction": "UP",
      "confidence": 0.9109,
      "entry_price": 70835.63,
      "exit_price": 70851.43,
      "result": "WIN",
      "profit": 0.46,
      "indicators": {
        "OpenVsCurrent": "UP",
        "BinanceOrderbook": "UP"
      },
      "window_start": "2026-02-08T22:15:00+00:00",
      "window_end": "2026-02-08T22:30:00+00:00",
      "buy_price_cents": 54,
      "edge": 0.3759,
      "entry_minute": 9
    },
    {
      "id": "bcbee2f3",
      "timestamp": "2026-02-08T22:27:00.616572+00:00",
      "strategy": "Ensemble",
      "direction": "UP",
      "confidence": 0.95,
      "entry_price": 70835.63,
      "exit_price": 70851.43,
      "result": "WIN",
      "profit": 0.22,
      "indicators": {
        "OpenVsCurrent": "UP"
      },
      "window_start": "2026-02-08T22:15:00+00:00",
      "window_end": "2026-02-08T22:30:00+00:00",
      "buy_price_cents": 78,
      "edge": 0.175,
      "entry_minute": 12
    },
    {
      "id": "d032e3f6",
      "timestamp": "2026-02-08T22:30:10.880489+00:00",
      "strategy": "Ensemble",
      "direction": "DOWN",
      "confidence": 0.8912,
      "entry_price": 70851.43,
      "exit_price": 70911.63,
      "result": "LOSS",
      "profit": -0.5,
      "indicators": {
        "OpenVsCurrent": "DOWN",
        "BinanceOrderbook": "DOWN",
        "OrderbookImbalance": "DOWN"
      },
      "window_start": "2026-02-08T22:30:00+00:00",
      "window_end": "2026-02-08T22:45:00+00:00",
      "buy_price_cents": 50,
      "edge": 0.3862,
      "entry_minute": 0
    },
    {
      "id": "1ccf5d82",
      "timestamp": "2026-02-08T22:31:05.454825+00:00",
      "strategy": "Ensemble",
      "direction": "DOWN",
      "confidence": 0.8953,
      "entry_price": 70851.43,
      "exit_price": 70911.63,
      "result": "LOSS",
      "profit": -0.5,
      "indicators": {
        "OpenVsCurrent": "DOWN",
        "OrderbookImbalance": "DOWN"
      },
      "window_start": "2026-02-08T22:30:00+00:00",
      "window_end": "2026-02-08T22:45:00+00:00",
      "buy_price_cents": 50,
      "edge": 0.3903,
      "entry_minute": 1
    }
  ]
}